plim/__init__.py
plim/console.py
plim/errors.py
plim/extensions.py
plim/lexer.py
plim/syntax.py
plim/unportable.py
plim/util.py
plim/adapters/__init__.py
plim/adapters/babelplugin.py
plim/adapters/pyramid_renderer.py
tests/adapters/__init__.py
tests/adapters/test_babelplugin.py
tests/django_test/__init__.py
Plim-1.0.0.dist-info/AUTHORS
Plim-1.0.0.dist-info/LICENSE
Plim-1.0.0.dist-info/METADATA
Plim-1.0.0.dist-info/WHEEL
Plim-1.0.0.dist-info/entry_points.txt
Plim-1.0.0.dist-info/top_level.txt
Plim-1.0.0.dist-info/RECORD
