Metadata-Version: 2.1
Name: Plim
Version: 1.0.0
Summary: Plim is a Python port of Ruby's Slim template language built on top of Mako Templates
Home-page: https://github.com/avanov/Plim
Download-URL: https://github.com/avanov/Plim
Author: Maxim Avanov
Author-email: maxim.avanov@gmail.com
Maintainer: Maxim Avanov
Maintainer-email: maxim.avanov@gmail.com
License: MIT
Keywords: mako templates ruby slim jade pyjade pyramid flask haml pyhaml
Classifier: Development Status :: 5 - Production/Stable
Classifier: Environment :: Web Environment
Classifier: Framework :: Pylons
Classifier: Framework :: Pyramid
Classifier: Framework :: TurboGears
Classifier: Intended Audience :: Developers
Classifier: License :: OSI Approved
Classifier: License :: OSI Approved :: MIT License
Classifier: Operating System :: MacOS
Classifier: Operating System :: Microsoft
Classifier: Operating System :: POSIX
Classifier: Programming Language :: Python
Classifier: Programming Language :: Python :: 3
Classifier: Topic :: Internet :: WWW/HTTP
Classifier: Topic :: Internet :: WWW/HTTP :: Dynamic Content
Classifier: Topic :: Software Development :: Libraries :: Python Modules
Classifier: Topic :: Software Development :: Pre-processors
Classifier: Topic :: Text Processing :: Markup :: HTML
License-File: LICENSE
License-File: AUTHORS
Requires-Dist: Mako (>=0.9.0)
Requires-Dist: babel (>=1.3)
Requires-Dist: docutils (>=0.3)
Requires-Dist: markdown2 (>=1.4.2)
Requires-Dist: PyExecJS (>=1.0.4)
Requires-Dist: CoffeeScript
Requires-Dist: pyScss (>=1.2.0.post3)
Requires-Dist: stylus (>=0.1.1)
